proxytunnel/__init__.py
proxytunnel-0.1.1.dist-info/LICENSE
proxytunnel-0.1.1.dist-info/METADATA
proxytunnel-0.1.1.dist-info/WHEEL
proxytunnel-0.1.1.dist-info/top_level.txt
proxytunnel-0.1.1.dist-info/RECORD
