Metadata-Version: 2.2
Name: proxytunnel
Version: 0.1.1
Summary: fast forward proxy tunnel
Home-page: https://github.com/workwhileweb/proxytunnel
Author: workwhileweb
Author-email: workwhileweb@gmail.com
Classifier: Programming Language :: Python :: 3
Classifier: License :: OSI Approved :: MIT License
Classifier: Operating System :: Microsoft :: Windows
Requires-Python: >=3.6
License-File: LICENSE
Requires-Dist: requests>=2.25.0
Dynamic: author
Dynamic: author-email
Dynamic: classifier
Dynamic: description
Dynamic: description-content-type
Dynamic: home-page
Dynamic: requires-dist
Dynamic: requires-python
Dynamic: summary
